{
	"easycom": {
	    "^tn-(.*)": "@/tuniao-ui/components/tn-$1/tn-$1.vue"
	},
	"pages": [ //pages数组中第一项表示应用启动页，参考：https://uniapp.dcloud.io/collocation/pages
		{
			"path": "pages/index/index",
			"style": {
				"navigationBarTitleText": "首页"
			}
		}
	    ,{
            "path" : "pages/account/account",
            "style" :                                                                                    
            {
                "navigationBarTitleText": "账号设置",
                "enablePullDownRefresh": false
            }
            
        }
        ,{
            "path" : "pages/login/login",
            "style" :                                                                                    
            {
                "navigationBarTitleText": "",
                "enablePullDownRefresh": false
            }
            
        }
    ],
	"globalStyle": {
		"navigationStyle": "custom",
		"navigationBarTextStyle": "black",
		"navigationBarTitleText": "在线答题",
		"navigationBarBackgroundColor": "#F8F8F8",
		"backgroundColor": "#F8F8F8"
	},
	"tabBar": {
		"color": "#7A7E83",
		"selectedColor": "#01BEFF",
		"borderStyle": "black",
		"backgroundColor": "#ffffff",
		"list": [{
			"pagePath": "pages/index/index",
			"selectedIconPath": "static/tabbar-main.png",
			"iconPath": "static/tabbar-main.png",
			"text": "首页"
		}, {
			"pagePath": "pages/account/account",
			"iconPath": "static/tabbar-account.png",
			"selectedIconPath": "static/tabbar-account.png",
			"text": "账号设置"
		}]
	}
}
